keras_recommenders
