Metadata-Version: 2.1
Name: keras-recommenders
Version: 0.0.3
Summary: A recommendation system models based Keras
Home-page: https://github.com/morningsky/keras-recommenders
Author: Mincai lai
Author-email: 757387961@qq.com
License: Apache-2.0
Keywords: ctr,click through rate,deep learning,keras,tensorflow,recommendation,deepctr
Platform: all
Classifier: Intended Audience :: Developers
Classifier: Intended Audience :: Education
Classifier: Intended Audience :: Science/Research
Classifier: Operating System :: OS Independent
Classifier: Natural Language :: Chinese (Simplified)
Classifier: Programming Language :: Python :: 3
Classifier: Programming Language :: Python :: 3.5
Classifier: Programming Language :: Python :: 3.6
Classifier: Programming Language :: Python :: 3.7
Classifier: Programming Language :: Python :: 3.8
Classifier: Topic :: Scientific/Engineering
Classifier: Topic :: Scientific/Engineering :: Artificial Intelligence
Classifier: Topic :: Software Development :: Libraries
Classifier: Topic :: Software Development :: Libraries :: Python Modules
Classifier: License :: OSI Approved :: Apache Software License
License-File: LICENSE.txt
